counsel/__init__.py
counsel/__main__.py
counsel/assets/templates/slack.md.j2
counsel/cli.py
counsel/counsel.py
counsel/models/__init__.py
counsel/models/counsel.py
counsel/models/syft.py
counsel/policy.py
counsel-0.1.2a0.dist-info/LICENSE
counsel-0.1.2a0.dist-info/METADATA
counsel-0.1.2a0.dist-info/WHEEL
counsel-0.1.2a0.dist-info/entry_points.txt
counsel-0.1.2a0.dist-info/RECORD
