Metadata-Version: 2.1
Name: counsel
Version: 0.1.2a0
Summary: A tool for monitoring the vulnerabilities of docker containers.
Home-page: https://github.com/evhart/counsel/
License: MIT
Author: Grégoire Burel
Author-email: evhart@users.noreply.github.com
Requires-Python: >=3.11,<4.0
Classifier: Development Status :: 3 - Alpha
Classifier: Intended Audience :: Developers
Classifier: Intended Audience :: System Administrators
Classifier: License :: OSI Approved :: MIT License
Classifier: Programming Language :: Python
Classifier: Programming Language :: Python :: 3
Classifier: Programming Language :: Python :: 3.11
Classifier: Programming Language :: Python :: 3
Classifier: Programming Language :: Python :: 3.11
Classifier: Programming Language :: Python :: Implementation :: PyPy
Classifier: Topic :: Communications
Classifier: Topic :: Security
Classifier: Topic :: System :: Monitoring
Classifier: Topic :: Utilities
Requires-Dist: apprise (>=1.3.0,<2.0.0)
Requires-Dist: cachetools (>=5.3.0,<6.0.0)
Requires-Dist: croniter (>=1.3.8,<2.0.0)
Requires-Dist: docker (>=6.0.1,<7.0.0)
Requires-Dist: jinja2 (>=3.1.2,<4.0.0)
Requires-Dist: pydantic (>=1.10.6,<2.0.0)
Requires-Dist: shellingham (>=1.5.0.post1,<2.0.0)
Requires-Dist: typer[all] (>=0.7.0,<0.8.0)
Requires-Dist: types-cachetools (>=5.3.0.4,<6.0.0.0)
Requires-Dist: types-croniter (>=1.3.2.6,<2.0.0.0)
Project-URL: Repository, https://github.com/evhart/counsel/
